resilient_python_cache/__init__.py
resilient_python_cache/cache.py
resilient_python_cache/config.py
resilient_python_cache/exceptions.py
resilient_python_cache-0.1.1.dist-info/LICENSE
resilient_python_cache-0.1.1.dist-info/METADATA
resilient_python_cache-0.1.1.dist-info/WHEEL
resilient_python_cache-0.1.1.dist-info/RECORD
